Pyramid110ZhongwenWendang/README.md
Pyramid110ZhongwenWendang/__init__.py
Pyramid110ZhongwenWendang/__main__.py
Pyramid110ZhongwenWendang/file.epub
Pyramid110ZhongwenWendang/index.html
Pyramid110ZhongwenWendang/css/__init__.py
Pyramid110ZhongwenWendang/css/annotations.css
Pyramid110ZhongwenWendang/css/main.css
Pyramid110ZhongwenWendang/css/normalize.css
Pyramid110ZhongwenWendang/css/popup.css
Pyramid110ZhongwenWendang/font/__init__.py
Pyramid110ZhongwenWendang/font/fontello.eot
Pyramid110ZhongwenWendang/font/fontello.svg
Pyramid110ZhongwenWendang/font/fontello.ttf
Pyramid110ZhongwenWendang/font/fontello.woff
Pyramid110ZhongwenWendang/img/__init__.py
Pyramid110ZhongwenWendang/img/annotator-glyph-sprite.png
Pyramid110ZhongwenWendang/img/annotator-icon-sprite.png
Pyramid110ZhongwenWendang/img/apple-touch-icon.png
Pyramid110ZhongwenWendang/img/cancelfullscreen.png
Pyramid110ZhongwenWendang/img/close.png
Pyramid110ZhongwenWendang/img/fullscreen.png
Pyramid110ZhongwenWendang/img/loader.gif
Pyramid110ZhongwenWendang/img/menu-icon.png
Pyramid110ZhongwenWendang/img/save.png
Pyramid110ZhongwenWendang/img/saved.png
Pyramid110ZhongwenWendang/img/settings-s.png
Pyramid110ZhongwenWendang/img/settings.png
Pyramid110ZhongwenWendang/img/star.png
Pyramid110ZhongwenWendang/js/__init__.py
Pyramid110ZhongwenWendang/js/epub.js
Pyramid110ZhongwenWendang/js/epub.min.js
Pyramid110ZhongwenWendang/js/epub.min.map
Pyramid110ZhongwenWendang/js/hooks.min.js
Pyramid110ZhongwenWendang/js/hooks.min.map
Pyramid110ZhongwenWendang/js/reader.js
Pyramid110ZhongwenWendang/js/reader.js.map
Pyramid110ZhongwenWendang/js/reader.min.js
Pyramid110ZhongwenWendang/js/reader.min.map
Pyramid110ZhongwenWendang/js/hooks/__init__.py
Pyramid110ZhongwenWendang/js/hooks/extensions/__init__.py
Pyramid110ZhongwenWendang/js/hooks/extensions/highlight.js
Pyramid110ZhongwenWendang/js/libs/__init__.py
Pyramid110ZhongwenWendang/js/libs/jquery.min.js
Pyramid110ZhongwenWendang/js/libs/localforage.min.js
pyramid_1_10_zhongwen_wendang-2024.3.5.0.dist-info/METADATA
pyramid_1_10_zhongwen_wendang-2024.3.5.0.dist-info/WHEEL
pyramid_1_10_zhongwen_wendang-2024.3.5.0.dist-info/entry_points.txt
pyramid_1_10_zhongwen_wendang-2024.3.5.0.dist-info/top_level.txt
pyramid_1_10_zhongwen_wendang-2024.3.5.0.dist-info/RECORD
